porechopx/__init__.py
porechopx/adapters.py
porechopx/logger.py
porechopx/main.py
porechopx/misc.py
porechopx/parser.py
porechopx/porechop.py
porechopx-0.2.0.dist-info/LICENSE
porechopx-0.2.0.dist-info/METADATA
porechopx-0.2.0.dist-info/WHEEL
porechopx-0.2.0.dist-info/entry_points.txt
porechopx-0.2.0.dist-info/RECORD
