Metadata-Version: 2.1
Name: porechopx
Version: 0.2.0
Summary: 
Author: kevinzjy
Author-email: kevinzjy1997@gmail.com
Requires-Python: >=3.10,<3.12
Classifier: Programming Language :: Python :: 3
Classifier: Programming Language :: Python :: 3.10
Classifier: Programming Language :: Python :: 3.11
Requires-Dist: click (>=8.1.7,<9.0.0)
Requires-Dist: edlib (>=1.3.9,<2.0.0)
Requires-Dist: needletail (>=0.5.0,<0.6.0)
Requires-Dist: numpy (>=2.1.0,<3.0.0)
Requires-Dist: parasail (>=1.3.4,<2.0.0)
Requires-Dist: tqdm (>=4.66.5,<5.0.0)
